iginx/__init__.py
iginx/cluster_info.py
iginx/dataset.py
iginx/session.py
iginx/time_series.py
iginx/thrift/__init__.py
iginx/thrift/rpc/IService.py
iginx/thrift/rpc/__init__.py
iginx/thrift/rpc/constants.py
iginx/thrift/rpc/ttypes.py
iginx/utils/__init__.py
iginx/utils/bitmap.py
iginx/utils/byte_utils.py
iginx-0.5.1.dist-info/METADATA
iginx-0.5.1.dist-info/WHEEL
iginx-0.5.1.dist-info/top_level.txt
iginx-0.5.1.dist-info/RECORD
