Metadata-Version: 2.1
Name: iginx
Version: 0.5.1
Summary: IginX Python Client
Home-page: https://github.com/thulab/IginX
Author: Zi Yuan
Author-email: ziy20@outlook.com
License: UNKNOWN
Platform: UNKNOWN
Classifier: Programming Language :: Python :: 3
Classifier: License :: OSI Approved :: Apache Software License
Classifier: Operating System :: OS Independent
Requires-Python: >=3.6
